mpd_inspector/__init__.py
mpd_inspector/inspector.py
mpd_inspector/namespaces.py
mpd_inspector/parser/__init__.py
mpd_inspector/parser/attribute_parsers.py
mpd_inspector/parser/enums.py
mpd_inspector/parser/exceptions.py
mpd_inspector/parser/mpd_tags.py
mpd_inspector/parser/parser.py
mpd_inspector/provenance.py
mpd_inspector/scte35/__init__.py
mpd_inspector/scte35/parser.py
mpd_inspector/scte35/scte35_enums.py
mpd_inspector/scte35/scte35_tags.py
mpd_inspector/scte35/scte35_xml.py
mpd_inspector/utils.py
mpd_inspector-1.2.1.dist-info/METADATA
mpd_inspector-1.2.1.dist-info/WHEEL
mpd_inspector-1.2.1.dist-info/licenses/LICENSE
mpd_inspector-1.2.1.dist-info/RECORD
