Metadata-Version: 2.4
Name: mpd-inspector
Version: 1.2.1
Summary: A module to parse, analyze and validate MPEG-DASH MPD
License: MIT
License-File: LICENSE
Author: Fabre Lambeau
Author-email: fabre.lambeau@gmail.com
Requires-Python: >=3.9,<4.0
Classifier: License :: OSI Approved :: MIT License
Classifier: Programming Language :: Python :: 3
Classifier: Programming Language :: Python :: 3.9
Classifier: Programming Language :: Python :: 3.10
Classifier: Programming Language :: Python :: 3.11
Classifier: Programming Language :: Python :: 3.12
Classifier: Programming Language :: Python :: 3.13
Classifier: Programming Language :: Python :: 3.14
Requires-Dist: isodate (>=0.6.1,<0.7.0)
Requires-Dist: lxml (>=5.2.2,<6.0.0)
Requires-Dist: threefive3 (>=3.0.19,<4.0.0)
